mchmm/__init__.py
mchmm/_hmm.py
mchmm/_mc.py
mchmm-0.4.5.dist-info/LICENSE
mchmm-0.4.5.dist-info/METADATA
mchmm-0.4.5.dist-info/WHEEL
mchmm-0.4.5.dist-info/top_level.txt
mchmm-0.4.5.dist-info/RECORD
